README.txt
setup.py
collective/__init__.py
collective.remove.rules.egg-info/PKG-INFO
collective.remove.rules.egg-info/SOURCES.txt
collective.remove.rules.egg-info/dependency_links.txt
collective.remove.rules.egg-info/entry_points.txt
collective.remove.rules.egg-info/namespace_packages.txt
collective.remove.rules.egg-info/not-zip-safe
collective.remove.rules.egg-info/requires.txt
collective.remove.rules.egg-info/top_level.txt
collective/remove/__init__.py
collective/remove/rules/__init__.py
collective/remove/rules/configure.zcml
collective/remove/rules/profiles/default/actions.xml
collective/remove/rules/profiles/default/metadata.xml
docs/HISTORY.txt