Metadata-Version: 1.0
Name: collective.remove.rules
Version: 0.1
Summary: Remove rules system from plone
Home-page: http://svn.plone.org/svn/collective/collective.remove/rules/trunk
Author: JeanMichel FRANCOIS
Author-email: jeanmichel.francois@makina-corpus.org
License: GPL
Platform: UNKNOWN
Classifier: Programming Language :: Python
